viml/__init__.py
viml-0.1.0.dist-info/METADATA
viml-0.1.0.dist-info/WHEEL
viml-0.1.0.dist-info/RECORD
